{
	"backtraceGraph" : 
	{
		"commands" : 
		[
			"install"
		],
		"files" : 
		[
			"external/SDL2_ttf/external/freetype/CMakeLists.txt"
		],
		"nodes" : 
		[
			{
				"file" : 0
			},
			{
				"command" : 0,
				"file" : 0,
				"line" : 576,
				"parent" : 0
			},
			{
				"command" : 0,
				"file" : 0,
				"line" : 584,
				"parent" : 0
			},
			{
				"command" : 0,
				"file" : 0,
				"line" : 638,
				"parent" : 0
			},
			{
				"command" : 0,
				"file" : 0,
				"line" : 649,
				"parent" : 0
			},
			{
				"command" : 0,
				"file" : 0,
				"line" : 657,
				"parent" : 0
			},
			{
				"command" : 0,
				"file" : 0,
				"line" : 662,
				"parent" : 0
			}
		]
	},
	"installers" : 
	[
		{
			"backtrace" : 1,
			"component" : "headers",
			"destination" : "include/freetype2",
			"paths" : 
			[
				{
					"from" : "external/SDL2_ttf/external/freetype/include",
					"to" : "."
				}
			],
			"type" : "directory"
		},
		{
			"backtrace" : 2,
			"component" : "headers",
			"destination" : "include/freetype2/freetype/config",
			"paths" : 
			[
				"android/app/.cxx/Debug/2h3d1g1b/arm64-v8a/SDL2_ttf/external/freetype/include/freetype/config/ftconfig.h",
				"android/app/.cxx/Debug/2h3d1g1b/arm64-v8a/SDL2_ttf/external/freetype/include/freetype/config/ftoption.h"
			],
			"type" : "file"
		},
		{
			"backtrace" : 3,
			"component" : "pkgconfig",
			"destination" : "lib/pkgconfig",
			"paths" : 
			[
				"android/app/.cxx/Debug/2h3d1g1b/arm64-v8a/SDL2_ttf/external/freetype/freetype2.pc"
			],
			"type" : "file"
		},
		{
			"backtrace" : 4,
			"component" : "Unspecified",
			"destination" : "lib",
			"paths" : 
			[
				"SDL2_ttf/external/freetype/libfreetyped.a"
			],
			"targetId" : "freetype::@8eecf364254debd0dde4",
			"targetIndex" : 7,
			"type" : "target"
		},
		{
			"backtrace" : 5,
			"component" : "headers",
			"destination" : "lib/cmake/freetype",
			"exportName" : "freetype-targets",
			"exportTargets" : 
			[
				{
					"id" : "freetype::@8eecf364254debd0dde4",
					"index" : 7
				},
				{
					"id" : "freetype-interface::@8eecf364254debd0dde4",
					"index" : 0
				}
			],
			"paths" : 
			[
				"SDL2_ttf/external/freetype/CMakeFiles/Export/lib/cmake/freetype/freetype-config.cmake"
			],
			"type" : "export"
		},
		{
			"backtrace" : 6,
			"component" : "headers",
			"destination" : "lib/cmake/freetype",
			"paths" : 
			[
				"android/app/.cxx/Debug/2h3d1g1b/arm64-v8a/SDL2_ttf/external/freetype/freetype-config-version.cmake"
			],
			"type" : "file"
		}
	],
	"paths" : 
	{
		"build" : "SDL2_ttf/external/freetype",
		"source" : "external/SDL2_ttf/external/freetype"
	}
}
